{".class":"MypyFile","_fullname":"stripe._customer_cash_balance_transaction","future_import_flags":[],"is_partial_stub_package":false,"is_stub":false,"names":{".class":"SymbolTable","BalanceTransaction":{".class":"SymbolTableNode","cross_ref":"stripe._balance_transaction.BalanceTransaction","kind":"Gdef"},"ClassVar":{".class":"SymbolTableNode","cross_ref":"typing.ClassVar","kind":"Gdef"},"Customer":{".class":"SymbolTableNode","cross_ref":"stripe._customer.Customer","kind":"Gdef"},"CustomerCashBalanceTransaction":{".class":"SymbolTableNode","kind":"Gdef","node":{".class":"TypeInfo","_promote":[],"abstract_attributes":[],"alt_promote":null,"bases":["stripe._stripe_object.StripeObject"],"dataclass_transform_spec":null,"declared_metaclass":null,"defn":{".class":"ClassDef","fullname":"stripe._customer_cash_balance_transaction.CustomerCashBalanceTransaction","name":"CustomerCashBalanceTransaction","type_vars":[]},"deletable_attributes":[],"deprecated":null,"flags":[],"fullname":"stripe._customer_cash_balance_transaction.CustomerCashBalanceTransaction","has_param_spec_type":false,"metaclass_type":"abc.ABCMeta","metadata":{},"module_name":"stripe._customer_cash_balance_transaction","mro":["stripe._customer_cash_balance_transaction.CustomerCashBalanceTransaction","stripe._stripe_object.StripeObject","builtins.dict","typing.MutableMapping","typing.Mapping","typing.Collection","typing.Iterable","typing.Container","builtins.object"],"names":{".class":"SymbolTable","AdjustedForOverdraft":{".class":"SymbolTableNode","kind":"Mdef","node":{".class":"TypeInfo","_promote":[],"abstract_attributes":[],"alt_promote":null,"bases":["stripe._stripe_object.StripeObject"],"dataclass_transform_spec":null,"declared_metaclass":null,"defn":{".class":"ClassDef","fullname":"stripe._customer_cash_balance_transaction.CustomerCashBalanceTransaction.AdjustedForOverdraft","name":"AdjustedForOverdraft","type_vars":[]},"deletable_attributes":[],"deprecated":null,"flags":[],"fullname":"stripe._customer_cash_balance_transaction.CustomerCashBalanceTransaction.AdjustedForOverdraft","has_param_spec_type":false,"metaclass_type":"abc.ABCMeta","metadata":{},"module_name":"stripe._customer_cash_balance_transaction","mro":["stripe._customer_cash_balance_transaction.CustomerCashBalanceTransaction.AdjustedForOverdraft","stripe._stripe_object.StripeObject","builtins.dict","typing.MutableMapping","typing.Mapping","typing.Collection","typing.Iterable","typing.Container","builtins.object"],"names":{".class":"SymbolTable","balance_transaction":{".class":"SymbolTableNode","kind":"Mdef","node":{".class":"Var","flags":["is_initialized_in_class","is_ready"],"fullname":"stripe._customer_cash_balance_transaction.CustomerCashBalanceTransaction.AdjustedForOverdraft.balance_transaction","name":"balance_transaction","setter_type":null,"type":{".class":"TypeAliasType","args":["stripe._balance_transaction.BalanceTransaction"],"type_ref":"stripe._expandable_field.ExpandableField"}}},"linked_transaction":{".class":"SymbolTableNode","kind":"Mdef","node":{".class":"Var","flags":["is_initialized_in_class","is_ready"],"fullname":"stripe._customer_cash_balance_transaction.CustomerCashBalanceTransaction.AdjustedForOverdraft.linked_transaction","name":"linked_transaction","setter_type":null,"type":{".class":"TypeAliasType","args":["stripe._customer_cash_balance_transaction.CustomerCashBalanceTransaction"],"type_ref":"stripe._expandable_field.ExpandableField"}}}},"self_type":{".class":"TypeVarType","default":{".class":"AnyType","missing_import_name":null,"source_any":null,"type_of_any":4},"fullname":"stripe._customer_cash_balance_transaction.CustomerCashBalanceTransaction.AdjustedForOverdraft.Self","id":0,"name":"Self","namespace":"","upper_bound":"stripe._customer_cash_balance_transaction.CustomerCashBalanceTransaction.AdjustedForOverdraft","values":[],"variance":0},"slots":null,"tuple_type":null,"type_vars":[],"typeddict_type":null}},"AppliedToPayment":{".class":"SymbolTableNode","kind":"Mdef","node":{".class":"TypeInfo","_promote":[],"abstract_attributes":[],"alt_promote":null,"bases":["stripe._stripe_object.StripeObject"],"dataclass_transform_spec":null,"declared_metaclass":null,"defn":{".class":"ClassDef","fullname":"stripe._customer_cash_balance_transaction.CustomerCashBalanceTransaction.AppliedToPayment","name":"AppliedToPayment","type_vars":[]},"deletable_attributes":[],"deprecated":null,"flags":[],"fullname":"stripe._customer_cash_balance_transaction.CustomerCashBalanceTransaction.AppliedToPayment","has_param_spec_type":false,"metaclass_type":"abc.ABCMeta","metadata":{},"module_name":"stripe._customer_cash_balance_transaction","mro":["stripe._customer_cash_balance_transaction.CustomerCashBalanceTransaction.AppliedToPayment","stripe._stripe_object.StripeObject","builtins.dict","typing.MutableMapping","typing.Mapping","typing.Collection","typing.Iterable","typing.Container","builtins.object"],"names":{".class":"SymbolTable","payment_intent":{".class":"SymbolTableNode","kind":"Mdef","node":{".class":"Var","flags":["is_initialized_in_class","is_ready"],"fullname":"stripe._customer_cash_balance_transaction.CustomerCashBalanceTransaction.AppliedToPayment.payment_intent","name":"payment_intent","setter_type":null,"type":{".class":"TypeAliasType","args":["stripe._payment_intent.PaymentIntent"],"type_ref":"stripe._expandable_field.ExpandableField"}}}},"self_type":{".class":"TypeVarType","default":{".class":"AnyType","missing_import_name":null,"source_any":null,"type_of_any":4},"fullname":"stripe._customer_cash_balance_transaction.CustomerCashBalanceTransaction.AppliedToPayment.Self","id":0,"name":"Self","namespace":"","upper_bound":"stripe._customer_cash_balance_transaction.CustomerCashBalanceTransaction.AppliedToPayment","values":[],"variance":0},"slots":null,"tuple_type":null,"type_vars":[],"typeddict_type":null}},"Funded":{".class":"SymbolTableNode","kind":"Mdef","node":{".class":"TypeInfo","_promote":[],"abstract_attributes":[],"alt_promote":null,"bases":["stripe._stripe_object.StripeObject"],"dataclass_transform_spec":null,"declared_metaclass":null,"defn":{".class":"ClassDef","fullname":"stripe._customer_cash_balance_transaction.CustomerCashBalanceTransaction.Funded","name":"Funded","type_vars":[]},"deletable_attributes":[],"deprecated":null,"flags":[],"fullname":"stripe._customer_cash_balance_transaction.CustomerCashBalanceTransaction.Funded","has_param_spec_type":false,"metaclass_type":"abc.ABCMeta","metadata":{},"module_name":"stripe._customer_cash_balance_transaction","mro":["stripe._customer_cash_balance_transaction.CustomerCashBalanceTransaction.Funded","stripe._stripe_object.StripeObject","builtins.dict","typing.MutableMapping","typing.Mapping","typing.Collection","typing.Iterable","typing.Container","builtins.object"],"names":{".class":"SymbolTable","BankTransfer":{".class":"SymbolTableNode","kind":"Mdef","node":{".class":"TypeInfo","_promote":[],"abstract_attributes":[],"alt_promote":null,"bases":["stripe._stripe_object.StripeObject"],"dataclass_transform_spec":null,"declared_metaclass":null,"defn":{".class":"ClassDef","fullname":"stripe._customer_cash_balance_transaction.CustomerCashBalanceTransaction.Funded.BankTransfer","name":"BankTransfer","type_vars":[]},"deletable_attributes":[],"deprecated":null,"flags":[],"fullname":"stripe._customer_cash_balance_transaction.CustomerCashBalanceTransaction.Funded.BankTransfer","has_param_spec_type":false,"metaclass_type":"abc.ABCMeta","metadata":{},"module_name":"stripe._customer_cash_balance_transaction","mro":["stripe._customer_cash_balance_transaction.CustomerCashBalanceTransaction.Funded.BankTransfer","stripe._stripe_object.StripeObject","builtins.dict","typing.MutableMapping","typing.Mapping","typing.Collection","typing.Iterable","typing.Container","builtins.object"],"names":{".class":"SymbolTable","EuBankTransfer":{".class":"SymbolTableNode","kind":"Mdef","node":{".class":"TypeInfo","_promote":[],"abstract_attributes":[],"alt_promote":null,"bases":["stripe._stripe_object.StripeObject"],"dataclass_transform_spec":null,"declared_metaclass":null,"defn":{".class":"ClassDef","fullname":"stripe._customer_cash_balance_transaction.CustomerCashBalanceTransaction.Funded.BankTransfer.EuBankTransfer","name":"EuBankTransfer","type_vars":[]},"deletable_attributes":[],"deprecated":null,"flags":[],"fullname":"stripe._customer_cash_balance_transaction.CustomerCashBalanceTransaction.Funded.BankTransfer.EuBankTransfer","has_param_spec_type":false,"metaclass_type":"abc.ABCMeta","metadata":{},"module_name":"stripe._customer_cash_balance_transaction","mro":["stripe._customer_cash_balance_transaction.CustomerCashBalanceTransaction.Funded.BankTransfer.EuBankTransfer","stripe._stripe_object.StripeObject","builtins.dict","typing.MutableMapping","typing.Mapping","typing.Collection","typing.Iterable","typing.Container","builtins.object"],"names":{".class":"SymbolTable","bic":{".class":"SymbolTableNode","kind":"Mdef","node":{".class":"Var","flags":["is_initialized_in_class","is_ready"],"fullname":"stripe._customer_cash_balance_transaction.CustomerCashBalanceTransaction.Funded.BankTransfer.EuBankTransfer.bic","name":"bic","setter_type":null,"type":{".class":"UnionType","items":["builtins.str",{".class":"NoneType"}],"uses_pep604_syntax":false}}},"iban_last4":{".class":"SymbolTableNode","kind":"Mdef","node":{".class":"Var","flags":["is_initialized_in_class","is_ready"],"fullname":"stripe._customer_cash_balance_transaction.CustomerCashBalanceTransaction.Funded.BankTransfer.EuBankTransfer.iban_last4","name":"iban_last4","setter_type":null,"type":{".class":"UnionType","items":["builtins.str",{".class":"NoneType"}],"uses_pep604_syntax":false}}},"sender_name":{".class":"SymbolTableNode","kind":"Mdef","node":{".class":"Var","flags":["is_initialized_in_class","is_ready"],"fullname":"stripe._customer_cash_balance_transaction.CustomerCashBalanceTransaction.Funded.BankTransfer.EuBankTransfer.sender_name","name":"sender_name","setter_type":null,"type":{".class":"UnionType","items":["builtins.str",{".class":"NoneType"}],"uses_pep604_syntax":false}}}},"self_type":{".class":"TypeVarType","default":{".class":"AnyType","missing_import_name":null,"source_any":null,"type_of_any":4},"fullname":"stripe._customer_cash_balance_transaction.CustomerCashBalanceTransaction.Funded.BankTransfer.EuBankTransfer.Self","id":0,"name":"Self","namespace":"","upper_bound":"stripe._customer_cash_balance_transaction.CustomerCashBalanceTransaction.Funded.BankTransfer.EuBankTransfer","values":[],"variance":0},"slots":null,"tuple_type":null,"type_vars":[],"typeddict_type":null}},"GbBankTransfer":{".class":"SymbolTableNode","kind":"Mdef","node":{".class":"TypeInfo","_promote":[],"abstract_attributes":[],"alt_promote":null,"bases":["stripe._stripe_object.StripeObject"],"dataclass_transform_spec":null,"declared_metaclass":null,"defn":{".class":"ClassDef","fullname":"stripe._customer_cash_balance_transaction.CustomerCashBalanceTransaction.Funded.BankTransfer.GbBankTransfer","name":"GbBankTransfer","type_vars":[]},"deletable_attributes":[],"deprecated":null,"flags":[],"fullname":"stripe._customer_cash_balance_transaction.CustomerCashBalanceTransaction.Funded.BankTransfer.GbBankTransfer","has_param_spec_type":false,"metaclass_type":"abc.ABCMeta","metadata":{},"module_name":"stripe._customer_cash_balance_transaction","mro":["stripe._customer_cash_balance_transaction.CustomerCashBalanceTransaction.Funded.BankTransfer.GbBankTransfer","stripe._stripe_object.StripeObject","builtins.dict","typing.MutableMapping","typing.Mapping","typing.Collection","typing.Iterable","typing.Container","builtins.object"],"names":{".class":"SymbolTable","account_number_last4":{".class":"SymbolTableNode","kind":"Mdef","node":{".class":"Var","flags":["is_initialized_in_class","is_ready"],"fullname":"stripe._customer_cash_balance_transaction.CustomerCashBalanceTransaction.Funded.BankTransfer.GbBankTransfer.account_number_last4","name":"account_number_last4","setter_type":null,"type":{".class":"UnionType","items":["builtins.str",{".class":"NoneType"}],"uses_pep604_syntax":false}}},"sender_name":{".class":"SymbolTableNode","kind":"Mdef","node":{".class":"Var","flags":["is_initialized_in_class","is_ready"],"fullname":"stripe._customer_cash_balance_transaction.CustomerCashBalanceTransaction.Funded.BankTransfer.GbBankTransfer.sender_name","name":"sender_name","setter_type":null,"type":{".class":"UnionType","items":["builtins.str",{".class":"NoneType"}],"uses_pep604_syntax":false}}},"sort_code":{".class":"SymbolTableNode","kind":"Mdef","node":{".class":"Var","flags":["is_initialized_in_class","is_ready"],"fullname":"stripe._customer_cash_balance_transaction.CustomerCashBalanceTransaction.Funded.BankTransfer.GbBankTransfer.sort_code","name":"sort_code","setter_type":null,"type":{".class":"UnionType","items":["builtins.str",{".class":"NoneType"}],"uses_pep604_syntax":false}}}},"self_type":{".class":"TypeVarType","default":{".class":"AnyType","missing_import_name":null,"source_any":null,"type_of_any":4},"fullname":"stripe._customer_cash_balance_transaction.CustomerCashBalanceTransaction.Funded.BankTransfer.GbBankTransfer.Self","id":0,"name":"Self","namespace":"","upper_bound":"stripe._customer_cash_balance_transaction.CustomerCashBalanceTransaction.Funded.BankTransfer.GbBankTransfer","values":[],"variance":0},"slots":null,"tuple_type":null,"type_vars":[],"typeddict_type":null}},"JpBankTransfer":{".class":"SymbolTableNode","kind":"Mdef","node":{".class":"TypeInfo","_promote":[],"abstract_attributes":[],"alt_promote":null,"bases":["stripe._stripe_object.StripeObject"],"dataclass_transform_spec":null,"declared_metaclass":null,"defn":{".class":"ClassDef","fullname":"stripe._customer_cash_balance_transaction.CustomerCashBalanceTransaction.Funded.BankTransfer.JpBankTransfer","name":"JpBankTransfer","type_vars":[]},"deletable_attributes":[],"deprecated":null,"flags":[],"fullname":"stripe._customer_cash_balance_transaction.CustomerCashBalanceTransaction.Funded.BankTransfer.JpBankTransfer","has_param_spec_type":false,"metaclass_type":"abc.ABCMeta","metadata":{},"module_name":"stripe._customer_cash_balance_transaction","mro":["stripe._customer_cash_balance_transaction.CustomerCashBalanceTransaction.Funded.BankTransfer.JpBankTransfer","stripe._stripe_object.StripeObject","builtins.dict","typing.MutableMapping","typing.Mapping","typing.Collection","typing.Iterable","typing.Container","builtins.object"],"names":{".class":"SymbolTable","sender_bank":{".class":"SymbolTableNode","kind":"Mdef","node":{".class":"Var","flags":["is_initialized_in_class","is_ready"],"fullname":"stripe._customer_cash_balance_transaction.CustomerCashBalanceTransaction.Funded.BankTransfer.JpBankTransfer.sender_bank","name":"sender_bank","setter_type":null,"type":{".class":"UnionType","items":["builtins.str",{".class":"NoneType"}],"uses_pep604_syntax":false}}},"sender_branch":{".class":"SymbolTableNode","kind":"Mdef","node":{".class":"Var","flags":["is_initialized_in_class","is_ready"],"fullname":"stripe._customer_cash_balance_transaction.CustomerCashBalanceTransaction.Funded.BankTransfer.JpBankTransfer.sender_branch","name":"sender_branch","setter_type":null,"type":{".class":"UnionType","items":["builtins.str",{".class":"NoneType"}],"uses_pep604_syntax":false}}},"sender_name":{".class":"SymbolTableNode","kind":"Mdef","node":{".class":"Var","flags":["is_initialized_in_class","is_ready"],"fullname":"stripe._customer_cash_balance_transaction.CustomerCashBalanceTransaction.Funded.BankTransfer.JpBankTransfer.sender_name","name":"sender_name","setter_type":null,"type":{".class":"UnionType","items":["builtins.str",{".class":"NoneType"}],"uses_pep604_syntax":false}}}},"self_type":{".class":"TypeVarType","default":{".class":"AnyType","missing_import_name":null,"source_any":null,"type_of_any":4},"fullname":"stripe._customer_cash_balance_transaction.CustomerCashBalanceTransaction.Funded.BankTransfer.JpBankTransfer.Self","id":0,"name":"Self","namespace":"","upper_bound":"stripe._customer_cash_balance_transaction.CustomerCashBalanceTransaction.Funded.BankTransfer.JpBankTransfer","values":[],"variance":0},"slots":null,"tuple_type":null,"type_vars":[],"typeddict_type":null}},"UsBankTransfer":{".class":"SymbolTableNode","kind":"Mdef","node":{".class":"TypeInfo","_promote":[],"abstract_attributes":[],"alt_promote":null,"bases":["stripe._stripe_object.StripeObject"],"dataclass_transform_spec":null,"declared_metaclass":null,"defn":{".class":"ClassDef","fullname":"stripe._customer_cash_balance_transaction.CustomerCashBalanceTransaction.Funded.BankTransfer.UsBankTransfer","name":"UsBankTransfer","type_vars":[]},"deletable_attributes":[],"deprecated":null,"flags":[],"fullname":"stripe._customer_cash_balance_transaction.CustomerCashBalanceTransaction.Funded.BankTransfer.UsBankTransfer","has_param_spec_type":false,"metaclass_type":"abc.ABCMeta","metadata":{},"module_name":"stripe._customer_cash_balance_transaction","mro":["stripe._customer_cash_balance_transaction.CustomerCashBalanceTransaction.Funded.BankTransfer.UsBankTransfer","stripe._stripe_object.StripeObject","builtins.dict","typing.MutableMapping","typing.Mapping","typing.Collection","typing.Iterable","typing.Container","builtins.object"],"names":{".class":"SymbolTable","network":{".class":"SymbolTableNode","kind":"Mdef","node":{".class":"Var","flags":["is_initialized_in_class","is_ready"],"fullname":"stripe._customer_cash_balance_transaction.CustomerCashBalanceTransaction.Funded.BankTransfer.UsBankTransfer.network","name":"network","setter_type":null,"type":{".class":"UnionType","items":[{".class":"LiteralType","fallback":"builtins.str","value":"ach"},{".class":"LiteralType","fallback":"builtins.str","value":"domestic_wire_us"},{".class":"LiteralType","fallback":"builtins.str","value":"swift"},{".class":"NoneType"}],"uses_pep604_syntax":false}}},"sender_name":{".class":"SymbolTableNode","kind":"Mdef","node":{".class":"Var","flags":["is_initialized_in_class","is_ready"],"fullname":"stripe._customer_cash_balance_transaction.CustomerCashBalanceTransaction.Funded.BankTransfer.UsBankTransfer.sender_name","name":"sender_name","setter_type":null,"type":{".class":"UnionType","items":["builtins.str",{".class":"NoneType"}],"uses_pep604_syntax":false}}}},"self_type":{".class":"TypeVarType","default":{".class":"AnyType","missing_import_name":null,"source_any":null,"type_of_any":4},"fullname":"stripe._customer_cash_balance_transaction.CustomerCashBalanceTransaction.Funded.BankTransfer.UsBankTransfer.Self","id":0,"name":"Self","namespace":"","upper_bound":"stripe._customer_cash_balance_transaction.CustomerCashBalanceTransaction.Funded.BankTransfer.UsBankTransfer","values":[],"variance":0},"slots":null,"tuple_type":null,"type_vars":[],"typeddict_type":null}},"_inner_class_types":{".class":"SymbolTableNode","kind":"Mdef","node":{".class":"Var","flags":["is_initialized_in_class","is_classvar","is_ready","is_inferred","has_explicit_value"],"fullname":"stripe._customer_cash_balance_transaction.CustomerCashBalanceTransaction.Funded.BankTransfer._inner_class_types","name":"_inner_class_types","setter_type":null,"type":{".class":"Instance","args":["builtins.str",{".class":"TypeType","item":"stripe._stripe_object.StripeObject"}],"extra_attrs":null,"type_ref":"builtins.dict"}}},"eu_bank_transfer":{".class":"SymbolTableNode","kind":"Mdef","node":{".class":"Var","flags":["is_initialized_in_class","is_ready"],"fullname":"stripe._customer_cash_balance_transaction.CustomerCashBalanceTransaction.Funded.BankTransfer.eu_bank_transfer","name":"eu_bank_transfer","setter_type":null,"type":{".class":"UnionType","items":["stripe._customer_cash_balance_transaction.CustomerCashBalanceTransaction.Funded.BankTransfer.EuBankTransfer",{".class":"NoneType"}],"uses_pep604_syntax":false}}},"gb_bank_transfer":{".class":"SymbolTableNode","kind":"Mdef","node":{".class":"Var","flags":["is_initialized_in_class","is_ready"],"fullname":"stripe._customer_cash_balance_transaction.CustomerCashBalanceTransaction.Funded.BankTransfer.gb_bank_transfer","name":"gb_bank_transfer","setter_type":null,"type":{".class":"UnionType","items":["stripe._customer_cash_balance_transaction.CustomerCashBalanceTransaction.Funded.BankTransfer.GbBankTransfer",{".class":"NoneType"}],"uses_pep604_syntax":false}}},"jp_bank_transfer":{".class":"SymbolTableNode","kind":"Mdef","node":{".class":"Var","flags":["is_initialized_in_class","is_ready"],"fullname":"stripe._customer_cash_balance_transaction.CustomerCashBalanceTransaction.Funded.BankTransfer.jp_bank_transfer","name":"jp_bank_transfer","setter_type":null,"type":{".class":"UnionType","items":["stripe._customer_cash_balance_transaction.CustomerCashBalanceTransaction.Funded.BankTransfer.JpBankTransfer",{".class":"NoneType"}],"uses_pep604_syntax":false}}},"reference":{".class":"SymbolTableNode","kind":"Mdef","node":{".class":"Var","flags":["is_initialized_in_class","is_ready"],"fullname":"stripe._customer_cash_balance_transaction.CustomerCashBalanceTransaction.Funded.BankTransfer.reference","name":"reference","setter_type":null,"type":{".class":"UnionType","items":["builtins.str",{".class":"NoneType"}],"uses_pep604_syntax":false}}},"type":{".class":"SymbolTableNode","kind":"Mdef","node":{".class":"Var","flags":["is_initialized_in_class","is_ready"],"fullname":"stripe._customer_cash_balance_transaction.CustomerCashBalanceTransaction.Funded.BankTransfer.type","name":"type","setter_type":null,"type":{".class":"UnionType","items":[{".class":"LiteralType","fallback":"builtins.str","value":"eu_bank_transfer"},{".class":"LiteralType","fallback":"builtins.str","value":"gb_bank_transfer"},{".class":"LiteralType","fallback":"builtins.str","value":"jp_bank_transfer"},{".class":"LiteralType","fallback":"builtins.str","value":"mx_bank_transfer"},{".class":"LiteralType","fallback":"builtins.str","value":"us_bank_transfer"}],"uses_pep604_syntax":false}}},"us_bank_transfer":{".class":"SymbolTableNode","kind":"Mdef","node":{".class":"Var","flags":["is_initialized_in_class","is_ready"],"fullname":"stripe._customer_cash_balance_transaction.CustomerCashBalanceTransaction.Funded.BankTransfer.us_bank_transfer","name":"us_bank_transfer","setter_type":null,"type":{".class":"UnionType","items":["stripe._customer_cash_balance_transaction.CustomerCashBalanceTransaction.Funded.BankTransfer.UsBankTransfer",{".class":"NoneType"}],"uses_pep604_syntax":false}}}},"self_type":{".class":"TypeVarType","default":{".class":"AnyType","missing_import_name":null,"source_any":null,"type_of_any":4},"fullname":"stripe._customer_cash_balance_transaction.CustomerCashBalanceTransaction.Funded.BankTransfer.Self","id":0,"name":"Self","namespace":"","upper_bound":"stripe._customer_cash_balance_transaction.CustomerCashBalanceTransaction.Funded.BankTransfer","values":[],"variance":0},"slots":null,"tuple_type":null,"type_vars":[],"typeddict_type":null}},"_inner_class_types":{".class":"SymbolTableNode","kind":"Mdef","node":{".class":"Var","flags":["is_initialized_in_class","is_classvar","is_ready","is_inferred","has_explicit_value"],"fullname":"stripe._customer_cash_balance_transaction.CustomerCashBalanceTransaction.Funded._inner_class_types","name":"_inner_class_types","setter_type":null,"type":{".class":"Instance","args":["builtins.str",{".class":"TypeType","item":"stripe._stripe_object.StripeObject"}],"extra_attrs":null,"type_ref":"builtins.dict"}}},"bank_transfer":{".class":"SymbolTableNode","kind":"Mdef","node":{".class":"Var","flags":["is_initialized_in_class","is_ready"],"fullname":"stripe._customer_cash_balance_transaction.CustomerCashBalanceTransaction.Funded.bank_transfer","name":"bank_transfer","setter_type":null,"type":"stripe._customer_cash_balance_transaction.CustomerCashBalanceTransaction.Funded.BankTransfer"}}},"self_type":{".class":"TypeVarType","default":{".class":"AnyType","missing_import_name":null,"source_any":null,"type_of_any":4},"fullname":"stripe._customer_cash_balance_transaction.CustomerCashBalanceTransaction.Funded.Self","id":0,"name":"Self","namespace":"","upper_bound":"stripe._customer_cash_balance_transaction.CustomerCashBalanceTransaction.Funded","values":[],"variance":0},"slots":null,"tuple_type":null,"type_vars":[],"typeddict_type":null}},"OBJECT_NAME":{".class":"SymbolTableNode","kind":"Mdef","node":{".class":"Var","flags":["is_initialized_in_class","is_classvar","is_ready","has_explicit_value"],"fullname":"stripe._customer_cash_balance_transaction.CustomerCashBalanceTransaction.OBJECT_NAME","name":"OBJECT_NAME","setter_type":null,"type":{".class":"LiteralType","fallback":"builtins.str","value":"customer_cash_balance_transaction"}}},"RefundedFromPayment":{".class":"SymbolTableNode","kind":"Mdef","node":{".class":"TypeInfo","_promote":[],"abstract_attributes":[],"alt_promote":null,"bases":["stripe._stripe_object.StripeObject"],"dataclass_transform_spec":null,"declared_metaclass":null,"defn":{".class":"ClassDef","fullname":"stripe._customer_cash_balance_transaction.CustomerCashBalanceTransaction.RefundedFromPayment","name":"RefundedFromPayment","type_vars":[]},"deletable_attributes":[],"deprecated":null,"flags":[],"fullname":"stripe._customer_cash_balance_transaction.CustomerCashBalanceTransaction.RefundedFromPayment","has_param_spec_type":false,"metaclass_type":"abc.ABCMeta","metadata":{},"module_name":"stripe._customer_cash_balance_transaction","mro":["stripe._customer_cash_balance_transaction.CustomerCashBalanceTransaction.RefundedFromPayment","stripe._stripe_object.StripeObject","builtins.dict","typing.MutableMapping","typing.Mapping","typing.Collection","typing.Iterable","typing.Container","builtins.object"],"names":{".class":"SymbolTable","refund":{".class":"SymbolTableNode","kind":"Mdef","node":{".class":"Var","flags":["is_initialized_in_class","is_ready"],"fullname":"stripe._customer_cash_balance_transaction.CustomerCashBalanceTransaction.RefundedFromPayment.refund","name":"refund","setter_type":null,"type":{".class":"TypeAliasType","args":["stripe._refund.Refund"],"type_ref":"stripe._expandable_field.ExpandableField"}}}},"self_type":{".class":"TypeVarType","default":{".class":"AnyType","missing_import_name":null,"source_any":null,"type_of_any":4},"fullname":"stripe._customer_cash_balance_transaction.CustomerCashBalanceTransaction.RefundedFromPayment.Self","id":0,"name":"Self","namespace":"","upper_bound":"stripe._customer_cash_balance_transaction.CustomerCashBalanceTransaction.RefundedFromPayment","values":[],"variance":0},"slots":null,"tuple_type":null,"type_vars":[],"typeddict_type":null}},"TransferredToBalance":{".class":"SymbolTableNode","kind":"Mdef","node":{".class":"TypeInfo","_promote":[],"abstract_attributes":[],"alt_promote":null,"bases":["stripe._stripe_object.StripeObject"],"dataclass_transform_spec":null,"declared_metaclass":null,"defn":{".class":"ClassDef","fullname":"stripe._customer_cash_balance_transaction.CustomerCashBalanceTransaction.TransferredToBalance","name":"TransferredToBalance","type_vars":[]},"deletable_attributes":[],"deprecated":null,"flags":[],"fullname":"stripe._customer_cash_balance_transaction.CustomerCashBalanceTransaction.TransferredToBalance","has_param_spec_type":false,"metaclass_type":"abc.ABCMeta","metadata":{},"module_name":"stripe._customer_cash_balance_transaction","mro":["stripe._customer_cash_balance_transaction.CustomerCashBalanceTransaction.TransferredToBalance","stripe._stripe_object.StripeObject","builtins.dict","typing.MutableMapping","typing.Mapping","typing.Collection","typing.Iterable","typing.Container","builtins.object"],"names":{".class":"SymbolTable","balance_transaction":{".class":"SymbolTableNode","kind":"Mdef","node":{".class":"Var","flags":["is_initialized_in_class","is_ready"],"fullname":"stripe._customer_cash_balance_transaction.CustomerCashBalanceTransaction.TransferredToBalance.balance_transaction","name":"balance_transaction","setter_type":null,"type":{".class":"TypeAliasType","args":["stripe._balance_transaction.BalanceTransaction"],"type_ref":"stripe._expandable_field.ExpandableField"}}}},"self_type":{".class":"TypeVarType","default":{".class":"AnyType","missing_import_name":null,"source_any":null,"type_of_any":4},"fullname":"stripe._customer_cash_balance_transaction.CustomerCashBalanceTransaction.TransferredToBalance.Self","id":0,"name":"Self","namespace":"","upper_bound":"stripe._customer_cash_balance_transaction.CustomerCashBalanceTransaction.TransferredToBalance","values":[],"variance":0},"slots":null,"tuple_type":null,"type_vars":[],"typeddict_type":null}},"UnappliedFromPayment":{".class":"SymbolTableNode","kind":"Mdef","node":{".class":"TypeInfo","_promote":[],"abstract_attributes":[],"alt_promote":null,"bases":["stripe._stripe_object.StripeObject"],"dataclass_transform_spec":null,"declared_metaclass":null,"defn":{".class":"ClassDef","fullname":"stripe._customer_cash_balance_transaction.CustomerCashBalanceTransaction.UnappliedFromPayment","name":"UnappliedFromPayment","type_vars":[]},"deletable_attributes":[],"deprecated":null,"flags":[],"fullname":"stripe._customer_cash_balance_transaction.CustomerCashBalanceTransaction.UnappliedFromPayment","has_param_spec_type":false,"metaclass_type":"abc.ABCMeta","metadata":{},"module_name":"stripe._customer_cash_balance_transaction","mro":["stripe._customer_cash_balance_transaction.CustomerCashBalanceTransaction.UnappliedFromPayment","stripe._stripe_object.StripeObject","builtins.dict","typing.MutableMapping","typing.Mapping","typing.Collection","typing.Iterable","typing.Container","builtins.object"],"names":{".class":"SymbolTable","payment_intent":{".class":"SymbolTableNode","kind":"Mdef","node":{".class":"Var","flags":["is_initialized_in_class","is_ready"],"fullname":"stripe._customer_cash_balance_transaction.CustomerCashBalanceTransaction.UnappliedFromPayment.payment_intent","name":"payment_intent","setter_type":null,"type":{".class":"TypeAliasType","args":["stripe._payment_intent.PaymentIntent"],"type_ref":"stripe._expandable_field.ExpandableField"}}}},"self_type":{".class":"TypeVarType","default":{".class":"AnyType","missing_import_name":null,"source_any":null,"type_of_any":4},"fullname":"stripe._customer_cash_balance_transaction.CustomerCashBalanceTransaction.UnappliedFromPayment.Self","id":0,"name":"Self","namespace":"","upper_bound":"stripe._customer_cash_balance_transaction.CustomerCashBalanceTransaction.UnappliedFromPayment","values":[],"variance":0},"slots":null,"tuple_type":null,"type_vars":[],"typeddict_type":null}},"_inner_class_types":{".class":"SymbolTableNode","kind":"Mdef","node":{".class":"Var","flags":["is_initialized_in_class","is_classvar","is_ready","is_inferred","has_explicit_value"],"fullname":"stripe._customer_cash_balance_transaction.CustomerCashBalanceTransaction._inner_class_types","name":"_inner_class_types","setter_type":null,"type":{".class":"Instance","args":["builtins.str",{".class":"TypeType","item":"stripe._stripe_object.StripeObject"}],"extra_attrs":null,"type_ref":"builtins.dict"}}},"adjusted_for_overdraft":{".class":"SymbolTableNode","kind":"Mdef","node":{".class":"Var","flags":["is_initialized_in_class","is_ready"],"fullname":"stripe._customer_cash_balance_transaction.CustomerCashBalanceTransaction.adjusted_for_overdraft","name":"adjusted_for_overdraft","setter_type":null,"type":{".class":"UnionType","items":["stripe._customer_cash_balance_transaction.CustomerCashBalanceTransaction.AdjustedForOverdraft",{".class":"NoneType"}],"uses_pep604_syntax":false}}},"applied_to_payment":{".class":"SymbolTableNode","kind":"Mdef","node":{".class":"Var","flags":["is_initialized_in_class","is_ready"],"fullname":"stripe._customer_cash_balance_transaction.CustomerCashBalanceTransaction.applied_to_payment","name":"applied_to_payment","setter_type":null,"type":{".class":"UnionType","items":["stripe._customer_cash_balance_transaction.CustomerCashBalanceTransaction.AppliedToPayment",{".class":"NoneType"}],"uses_pep604_syntax":false}}},"created":{".class":"SymbolTableNode","kind":"Mdef","node":{".class":"Var","flags":["is_initialized_in_class","is_ready"],"fullname":"stripe._customer_cash_balance_transaction.CustomerCashBalanceTransaction.created","name":"created","setter_type":null,"type":"builtins.int"}},"currency":{".class":"SymbolTableNode","kind":"Mdef","node":{".class":"Var","flags":["is_initialized_in_class","is_ready"],"fullname":"stripe._customer_cash_balance_transaction.CustomerCashBalanceTransaction.currency","name":"currency","setter_type":null,"type":"builtins.str"}},"customer":{".class":"SymbolTableNode","kind":"Mdef","node":{".class":"Var","flags":["is_initialized_in_class","is_ready"],"fullname":"stripe._customer_cash_balance_transaction.CustomerCashBalanceTransaction.customer","name":"customer","setter_type":null,"type":{".class":"TypeAliasType","args":["stripe._customer.Customer"],"type_ref":"stripe._expandable_field.ExpandableField"}}},"ending_balance":{".class":"SymbolTableNode","kind":"Mdef","node":{".class":"Var","flags":["is_initialized_in_class","is_ready"],"fullname":"stripe._customer_cash_balance_transaction.CustomerCashBalanceTransaction.ending_balance","name":"ending_balance","setter_type":null,"type":"builtins.int"}},"funded":{".class":"SymbolTableNode","kind":"Mdef","node":{".class":"Var","flags":["is_initialized_in_class","is_ready"],"fullname":"stripe._customer_cash_balance_transaction.CustomerCashBalanceTransaction.funded","name":"funded","setter_type":null,"type":{".class":"UnionType","items":["stripe._customer_cash_balance_transaction.CustomerCashBalanceTransaction.Funded",{".class":"NoneType"}],"uses_pep604_syntax":false}}},"id":{".class":"SymbolTableNode","kind":"Mdef","node":{".class":"Var","flags":["is_initialized_in_class","is_ready"],"fullname":"stripe._customer_cash_balance_transaction.CustomerCashBalanceTransaction.id","name":"id","setter_type":null,"type":"builtins.str"}},"livemode":{".class":"SymbolTableNode","kind":"Mdef","node":{".class":"Var","flags":["is_initialized_in_class","is_ready"],"fullname":"stripe._customer_cash_balance_transaction.CustomerCashBalanceTransaction.livemode","name":"livemode","setter_type":null,"type":"builtins.bool"}},"net_amount":{".class":"SymbolTableNode","kind":"Mdef","node":{".class":"Var","flags":["is_initialized_in_class","is_ready"],"fullname":"stripe._customer_cash_balance_transaction.CustomerCashBalanceTransaction.net_amount","name":"net_amount","setter_type":null,"type":"builtins.int"}},"object":{".class":"SymbolTableNode","kind":"Mdef","node":{".class":"Var","flags":["is_initialized_in_class","is_ready"],"fullname":"stripe._customer_cash_balance_transaction.CustomerCashBalanceTransaction.object","name":"object","setter_type":null,"type":{".class":"LiteralType","fallback":"builtins.str","value":"customer_cash_balance_transaction"}}},"refunded_from_payment":{".class":"SymbolTableNode","kind":"Mdef","node":{".class":"Var","flags":["is_initialized_in_class","is_ready"],"fullname":"stripe._customer_cash_balance_transaction.CustomerCashBalanceTransaction.refunded_from_payment","name":"refunded_from_payment","setter_type":null,"type":{".class":"UnionType","items":["stripe._customer_cash_balance_transaction.CustomerCashBalanceTransaction.RefundedFromPayment",{".class":"NoneType"}],"uses_pep604_syntax":false}}},"transferred_to_balance":{".class":"SymbolTableNode","kind":"Mdef","node":{".class":"Var","flags":["is_initialized_in_class","is_ready"],"fullname":"stripe._customer_cash_balance_transaction.CustomerCashBalanceTransaction.transferred_to_balance","name":"transferred_to_balance","setter_type":null,"type":{".class":"UnionType","items":["stripe._customer_cash_balance_transaction.CustomerCashBalanceTransaction.TransferredToBalance",{".class":"NoneType"}],"uses_pep604_syntax":false}}},"type":{".class":"SymbolTableNode","kind":"Mdef","node":{".class":"Var","flags":["is_initialized_in_class","is_ready"],"fullname":"stripe._customer_cash_balance_transaction.CustomerCashBalanceTransaction.type","name":"type","setter_type":null,"type":{".class":"UnionType","items":[{".class":"LiteralType","fallback":"builtins.str","value":"adjusted_for_overdraft"},{".class":"LiteralType","fallback":"builtins.str","value":"applied_to_payment"},{".class":"LiteralType","fallback":"builtins.str","value":"funded"},{".class":"LiteralType","fallback":"builtins.str","value":"funding_reversed"},{".class":"LiteralType","fallback":"builtins.str","value":"refunded_from_payment"},{".class":"LiteralType","fallback":"builtins.str","value":"return_canceled"},{".class":"LiteralType","fallback":"builtins.str","value":"return_initiated"},{".class":"LiteralType","fallback":"builtins.str","value":"transferred_to_balance"},{".class":"LiteralType","fallback":"builtins.str","value":"unapplied_from_payment"}],"uses_pep604_syntax":false}}},"unapplied_from_payment":{".class":"SymbolTableNode","kind":"Mdef","node":{".class":"Var","flags":["is_initialized_in_class","is_ready"],"fullname":"stripe._customer_cash_balance_transaction.CustomerCashBalanceTransaction.unapplied_from_payment","name":"unapplied_from_payment","setter_type":null,"type":{".class":"UnionType","items":["stripe._customer_cash_balance_transaction.CustomerCashBalanceTransaction.UnappliedFromPayment",{".class":"NoneType"}],"uses_pep604_syntax":false}}}},"self_type":{".class":"TypeVarType","default":{".class":"AnyType","missing_import_name":null,"source_any":null,"type_of_any":4},"fullname":"stripe._customer_cash_balance_transaction.CustomerCashBalanceTransaction.Self","id":0,"name":"Self","namespace":"","upper_bound":"stripe._customer_cash_balance_transaction.CustomerCashBalanceTransaction","values":[],"variance":0},"slots":null,"tuple_type":null,"type_vars":[],"typeddict_type":null}},"ExpandableField":{".class":"SymbolTableNode","cross_ref":"stripe._expandable_field.ExpandableField","kind":"Gdef"},"Literal":{".class":"SymbolTableNode","cross_ref":"typing_extensions.Literal","kind":"Gdef"},"Optional":{".class":"SymbolTableNode","cross_ref":"typing.Optional","kind":"Gdef"},"PaymentIntent":{".class":"SymbolTableNode","cross_ref":"stripe._payment_intent.PaymentIntent","kind":"Gdef"},"Refund":{".class":"SymbolTableNode","cross_ref":"stripe._refund.Refund","kind":"Gdef"},"StripeObject":{".class":"SymbolTableNode","cross_ref":"stripe._stripe_object.StripeObject","kind":"Gdef"},"TYPE_CHECKING":{".class":"SymbolTableNode","cross_ref":"typing.TYPE_CHECKING","kind":"Gdef"},"__annotations__":{".class":"SymbolTableNode","kind":"Gdef","node":{".class":"Var","flags":["is_ready"],"fullname":"stripe._customer_cash_balance_transaction.__annotations__","name":"__annotations__","setter_type":null,"type":{".class":"Instance","args":["builtins.str",{".class":"AnyType","missing_import_name":null,"source_any":null,"type_of_any":6}],"extra_attrs":null,"type_ref":"builtins.dict"}}},"__doc__":{".class":"SymbolTableNode","kind":"Gdef","node":{".class":"Var","flags":["is_ready"],"fullname":"stripe._customer_cash_balance_transaction.__doc__","name":"__doc__","setter_type":null,"type":"builtins.str"}},"__file__":{".class":"SymbolTableNode","kind":"Gdef","node":{".class":"Var","flags":["is_ready"],"fullname":"stripe._customer_cash_balance_transaction.__file__","name":"__file__","setter_type":null,"type":"builtins.str"}},"__name__":{".class":"SymbolTableNode","kind":"Gdef","node":{".class":"Var","flags":["is_ready"],"fullname":"stripe._customer_cash_balance_transaction.__name__","name":"__name__","setter_type":null,"type":"builtins.str"}},"__package__":{".class":"SymbolTableNode","kind":"Gdef","node":{".class":"Var","flags":["is_ready"],"fullname":"stripe._customer_cash_balance_transaction.__package__","name":"__package__","setter_type":null,"type":"builtins.str"}},"__spec__":{".class":"SymbolTableNode","kind":"Gdef","node":{".class":"Var","flags":["is_ready"],"fullname":"stripe._customer_cash_balance_transaction.__spec__","name":"__spec__","setter_type":null,"type":"_frozen_importlib.ModuleSpec"}}},"path":"C:\\Users\\nirma\\AppData\\Local\\Programs\\Python\\Python313\\Lib\\site-packages\\stripe\\_customer_cash_balance_transaction.py"}