{".class":"MypyFile","_fullname":"stripe._v1_services","future_import_flags":[],"is_partial_stub_package":false,"is_stub":false,"names":{".class":"SymbolTable","AccountLinkService":{".class":"SymbolTableNode","cross_ref":"stripe._account_link_service.AccountLinkService","kind":"Gdef"},"AccountService":{".class":"SymbolTableNode","cross_ref":"stripe._account_service.AccountService","kind":"Gdef"},"AccountSessionService":{".class":"SymbolTableNode","cross_ref":"stripe._account_session_service.AccountSessionService","kind":"Gdef"},"ApplePayDomainService":{".class":"SymbolTableNode","cross_ref":"stripe._apple_pay_domain_service.ApplePayDomainService","kind":"Gdef"},"ApplicationFeeService":{".class":"SymbolTableNode","cross_ref":"stripe._application_fee_service.ApplicationFeeService","kind":"Gdef"},"AppsService":{".class":"SymbolTableNode","cross_ref":"stripe._apps_service.AppsService","kind":"Gdef"},"BalanceService":{".class":"SymbolTableNode","cross_ref":"stripe._balance_service.BalanceService","kind":"Gdef"},"BalanceSettingsService":{".class":"SymbolTableNode","cross_ref":"stripe._balance_settings_service.BalanceSettingsService","kind":"Gdef"},"BalanceTransactionService":{".class":"SymbolTableNode","cross_ref":"stripe._balance_transaction_service.BalanceTransactionService","kind":"Gdef"},"BillingPortalService":{".class":"SymbolTableNode","cross_ref":"stripe._billing_portal_service.BillingPortalService","kind":"Gdef"},"BillingService":{".class":"SymbolTableNode","cross_ref":"stripe._billing_service.BillingService","kind":"Gdef"},"ChargeService":{".class":"SymbolTableNode","cross_ref":"stripe._charge_service.ChargeService","kind":"Gdef"},"CheckoutService":{".class":"SymbolTableNode","cross_ref":"stripe._checkout_service.CheckoutService","kind":"Gdef"},"ClimateService":{".class":"SymbolTableNode","cross_ref":"stripe._climate_service.ClimateService","kind":"Gdef"},"ConfirmationTokenService":{".class":"SymbolTableNode","cross_ref":"stripe._confirmation_token_service.ConfirmationTokenService","kind":"Gdef"},"CountrySpecService":{".class":"SymbolTableNode","cross_ref":"stripe._country_spec_service.CountrySpecService","kind":"Gdef"},"CouponService":{".class":"SymbolTableNode","cross_ref":"stripe._coupon_service.CouponService","kind":"Gdef"},"CreditNoteService":{".class":"SymbolTableNode","cross_ref":"stripe._credit_note_service.CreditNoteService","kind":"Gdef"},"CustomerService":{".class":"SymbolTableNode","cross_ref":"stripe._customer_service.CustomerService","kind":"Gdef"},"CustomerSessionService":{".class":"SymbolTableNode","cross_ref":"stripe._customer_session_service.CustomerSessionService","kind":"Gdef"},"DisputeService":{".class":"SymbolTableNode","cross_ref":"stripe._dispute_service.DisputeService","kind":"Gdef"},"EntitlementsService":{".class":"SymbolTableNode","cross_ref":"stripe._entitlements_service.EntitlementsService","kind":"Gdef"},"EphemeralKeyService":{".class":"SymbolTableNode","cross_ref":"stripe._ephemeral_key_service.EphemeralKeyService","kind":"Gdef"},"EventService":{".class":"SymbolTableNode","cross_ref":"stripe._event_service.EventService","kind":"Gdef"},"ExchangeRateService":{".class":"SymbolTableNode","cross_ref":"stripe._exchange_rate_service.ExchangeRateService","kind":"Gdef"},"FileLinkService":{".class":"SymbolTableNode","cross_ref":"stripe._file_link_service.FileLinkService","kind":"Gdef"},"FileService":{".class":"SymbolTableNode","cross_ref":"stripe._file_service.FileService","kind":"Gdef"},"FinancialConnectionsService":{".class":"SymbolTableNode","cross_ref":"stripe._financial_connections_service.FinancialConnectionsService","kind":"Gdef"},"ForwardingService":{".class":"SymbolTableNode","cross_ref":"stripe._forwarding_service.ForwardingService","kind":"Gdef"},"IdentityService":{".class":"SymbolTableNode","cross_ref":"stripe._identity_service.IdentityService","kind":"Gdef"},"InvoiceItemService":{".class":"SymbolTableNode","cross_ref":"stripe._invoice_item_service.InvoiceItemService","kind":"Gdef"},"InvoicePaymentService":{".class":"SymbolTableNode","cross_ref":"stripe._invoice_payment_service.InvoicePaymentService","kind":"Gdef"},"InvoiceRenderingTemplateService":{".class":"SymbolTableNode","cross_ref":"stripe._invoice_rendering_template_service.InvoiceRenderingTemplateService","kind":"Gdef"},"InvoiceService":{".class":"SymbolTableNode","cross_ref":"stripe._invoice_service.InvoiceService","kind":"Gdef"},"IssuingService":{".class":"SymbolTableNode","cross_ref":"stripe._issuing_service.IssuingService","kind":"Gdef"},"MandateService":{".class":"SymbolTableNode","cross_ref":"stripe._mandate_service.MandateService","kind":"Gdef"},"PaymentIntentService":{".class":"SymbolTableNode","cross_ref":"stripe._payment_intent_service.PaymentIntentService","kind":"Gdef"},"PaymentLinkService":{".class":"SymbolTableNode","cross_ref":"stripe._payment_link_service.PaymentLinkService","kind":"Gdef"},"PaymentMethodConfigurationService":{".class":"SymbolTableNode","cross_ref":"stripe._payment_method_configuration_service.PaymentMethodConfigurationService","kind":"Gdef"},"PaymentMethodDomainService":{".class":"SymbolTableNode","cross_ref":"stripe._payment_method_domain_service.PaymentMethodDomainService","kind":"Gdef"},"PaymentMethodService":{".class":"SymbolTableNode","cross_ref":"stripe._payment_method_service.PaymentMethodService","kind":"Gdef"},"PayoutService":{".class":"SymbolTableNode","cross_ref":"stripe._payout_service.PayoutService","kind":"Gdef"},"PlanService":{".class":"SymbolTableNode","cross_ref":"stripe._plan_service.PlanService","kind":"Gdef"},"PriceService":{".class":"SymbolTableNode","cross_ref":"stripe._price_service.PriceService","kind":"Gdef"},"ProductService":{".class":"SymbolTableNode","cross_ref":"stripe._product_service.ProductService","kind":"Gdef"},"PromotionCodeService":{".class":"SymbolTableNode","cross_ref":"stripe._promotion_code_service.PromotionCodeService","kind":"Gdef"},"QuoteService":{".class":"SymbolTableNode","cross_ref":"stripe._quote_service.QuoteService","kind":"Gdef"},"RadarService":{".class":"SymbolTableNode","cross_ref":"stripe._radar_service.RadarService","kind":"Gdef"},"RefundService":{".class":"SymbolTableNode","cross_ref":"stripe._refund_service.RefundService","kind":"Gdef"},"ReportingService":{".class":"SymbolTableNode","cross_ref":"stripe._reporting_service.ReportingService","kind":"Gdef"},"ReviewService":{".class":"SymbolTableNode","cross_ref":"stripe._review_service.ReviewService","kind":"Gdef"},"SetupAttemptService":{".class":"SymbolTableNode","cross_ref":"stripe._setup_attempt_service.SetupAttemptService","kind":"Gdef"},"SetupIntentService":{".class":"SymbolTableNode","cross_ref":"stripe._setup_intent_service.SetupIntentService","kind":"Gdef"},"ShippingRateService":{".class":"SymbolTableNode","cross_ref":"stripe._shipping_rate_service.ShippingRateService","kind":"Gdef"},"SigmaService":{".class":"SymbolTableNode","cross_ref":"stripe._sigma_service.SigmaService","kind":"Gdef"},"SourceService":{".class":"SymbolTableNode","cross_ref":"stripe._source_service.SourceService","kind":"Gdef"},"StripeService":{".class":"SymbolTableNode","cross_ref":"stripe._stripe_service.StripeService","kind":"Gdef"},"SubscriptionItemService":{".class":"SymbolTableNode","cross_ref":"stripe._subscription_item_service.SubscriptionItemService","kind":"Gdef"},"SubscriptionScheduleService":{".class":"SymbolTableNode","cross_ref":"stripe._subscription_schedule_service.SubscriptionScheduleService","kind":"Gdef"},"SubscriptionService":{".class":"SymbolTableNode","cross_ref":"stripe._subscription_service.SubscriptionService","kind":"Gdef"},"TaxCodeService":{".class":"SymbolTableNode","cross_ref":"stripe._tax_code_service.TaxCodeService","kind":"Gdef"},"TaxIdService":{".class":"SymbolTableNode","cross_ref":"stripe._tax_id_service.TaxIdService","kind":"Gdef"},"TaxRateService":{".class":"SymbolTableNode","cross_ref":"stripe._tax_rate_service.TaxRateService","kind":"Gdef"},"TaxService":{".class":"SymbolTableNode","cross_ref":"stripe._tax_service.TaxService","kind":"Gdef"},"TerminalService":{".class":"SymbolTableNode","cross_ref":"stripe._terminal_service.TerminalService","kind":"Gdef"},"TestHelpersService":{".class":"SymbolTableNode","cross_ref":"stripe._test_helpers_service.TestHelpersService","kind":"Gdef"},"TokenService":{".class":"SymbolTableNode","cross_ref":"stripe._token_service.TokenService","kind":"Gdef"},"TopupService":{".class":"SymbolTableNode","cross_ref":"stripe._topup_service.TopupService","kind":"Gdef"},"TransferService":{".class":"SymbolTableNode","cross_ref":"stripe._transfer_service.TransferService","kind":"Gdef"},"TreasuryService":{".class":"SymbolTableNode","cross_ref":"stripe._treasury_service.TreasuryService","kind":"Gdef"},"V1Services":{".class":"SymbolTableNode","kind":"Gdef","node":{".class":"TypeInfo","_promote":[],"abstract_attributes":[],"alt_promote":null,"bases":["stripe._stripe_service.StripeService"],"dataclass_transform_spec":null,"declared_metaclass":null,"defn":{".class":"ClassDef","fullname":"stripe._v1_services.V1Services","name":"V1Services","type_vars":[]},"deletable_attributes":[],"deprecated":null,"flags":[],"fullname":"stripe._v1_services.V1Services","has_param_spec_type":false,"metaclass_type":null,"metadata":{},"module_name":"stripe._v1_services","mro":["stripe._v1_services.V1Services","stripe._stripe_service.StripeService","builtins.object"],"names":{".class":"SymbolTable","__init__":{".class":"SymbolTableNode","kind":"Mdef","node":{".class":"FuncDef","abstract_status":0,"arg_kinds":[0,0],"arg_names":["self","requestor"],"dataclass_transform_spec":null,"deprecated":null,"flags":[],"fullname":"stripe._v1_services.V1Services.__init__","name":"__init__","original_first_arg":"self","type":null}},"account_links":{".class":"SymbolTableNode","implicit":true,"kind":"Mdef","node":{".class":"Var","flags":["is_ready","is_inferred"],"fullname":"stripe._v1_services.V1Services.account_links","name":"account_links","setter_type":null,"type":{".class":"AnyType","missing_import_name":null,"source_any":null,"type_of_any":1}}},"account_sessions":{".class":"SymbolTableNode","implicit":true,"kind":"Mdef","node":{".class":"Var","flags":["is_ready","is_inferred"],"fullname":"stripe._v1_services.V1Services.account_sessions","name":"account_sessions","setter_type":null,"type":{".class":"AnyType","missing_import_name":null,"source_any":null,"type_of_any":1}}},"accounts":{".class":"SymbolTableNode","implicit":true,"kind":"Mdef","node":{".class":"Var","flags":["is_ready","is_inferred"],"fullname":"stripe._v1_services.V1Services.accounts","name":"accounts","setter_type":null,"type":{".class":"AnyType","missing_import_name":null,"source_any":null,"type_of_any":1}}},"apple_pay_domains":{".class":"SymbolTableNode","implicit":true,"kind":"Mdef","node":{".class":"Var","flags":["is_ready","is_inferred"],"fullname":"stripe._v1_services.V1Services.apple_pay_domains","name":"apple_pay_domains","setter_type":null,"type":{".class":"AnyType","missing_import_name":null,"source_any":null,"type_of_any":1}}},"application_fees":{".class":"SymbolTableNode","implicit":true,"kind":"Mdef","node":{".class":"Var","flags":["is_ready","is_inferred"],"fullname":"stripe._v1_services.V1Services.application_fees","name":"application_fees","setter_type":null,"type":{".class":"AnyType","missing_import_name":null,"source_any":null,"type_of_any":1}}},"apps":{".class":"SymbolTableNode","implicit":true,"kind":"Mdef","node":{".class":"Var","flags":["is_ready","is_inferred"],"fullname":"stripe._v1_services.V1Services.apps","name":"apps","setter_type":null,"type":{".class":"AnyType","missing_import_name":null,"source_any":null,"type_of_any":1}}},"balance":{".class":"SymbolTableNode","implicit":true,"kind":"Mdef","node":{".class":"Var","flags":["is_ready","is_inferred"],"fullname":"stripe._v1_services.V1Services.balance","name":"balance","setter_type":null,"type":{".class":"AnyType","missing_import_name":null,"source_any":null,"type_of_any":1}}},"balance_settings":{".class":"SymbolTableNode","implicit":true,"kind":"Mdef","node":{".class":"Var","flags":["is_ready","is_inferred"],"fullname":"stripe._v1_services.V1Services.balance_settings","name":"balance_settings","setter_type":null,"type":{".class":"AnyType","missing_import_name":null,"source_any":null,"type_of_any":1}}},"balance_transactions":{".class":"SymbolTableNode","implicit":true,"kind":"Mdef","node":{".class":"Var","flags":["is_ready","is_inferred"],"fullname":"stripe._v1_services.V1Services.balance_transactions","name":"balance_transactions","setter_type":null,"type":{".class":"AnyType","missing_import_name":null,"source_any":null,"type_of_any":1}}},"billing":{".class":"SymbolTableNode","implicit":true,"kind":"Mdef","node":{".class":"Var","flags":["is_ready","is_inferred"],"fullname":"stripe._v1_services.V1Services.billing","name":"billing","setter_type":null,"type":{".class":"AnyType","missing_import_name":null,"source_any":null,"type_of_any":1}}},"billing_portal":{".class":"SymbolTableNode","implicit":true,"kind":"Mdef","node":{".class":"Var","flags":["is_ready","is_inferred"],"fullname":"stripe._v1_services.V1Services.billing_portal","name":"billing_portal","setter_type":null,"type":{".class":"AnyType","missing_import_name":null,"source_any":null,"type_of_any":1}}},"charges":{".class":"SymbolTableNode","implicit":true,"kind":"Mdef","node":{".class":"Var","flags":["is_ready","is_inferred"],"fullname":"stripe._v1_services.V1Services.charges","name":"charges","setter_type":null,"type":{".class":"AnyType","missing_import_name":null,"source_any":null,"type_of_any":1}}},"checkout":{".class":"SymbolTableNode","implicit":true,"kind":"Mdef","node":{".class":"Var","flags":["is_ready","is_inferred"],"fullname":"stripe._v1_services.V1Services.checkout","name":"checkout","setter_type":null,"type":{".class":"AnyType","missing_import_name":null,"source_any":null,"type_of_any":1}}},"climate":{".class":"SymbolTableNode","implicit":true,"kind":"Mdef","node":{".class":"Var","flags":["is_ready","is_inferred"],"fullname":"stripe._v1_services.V1Services.climate","name":"climate","setter_type":null,"type":{".class":"AnyType","missing_import_name":null,"source_any":null,"type_of_any":1}}},"confirmation_tokens":{".class":"SymbolTableNode","implicit":true,"kind":"Mdef","node":{".class":"Var","flags":["is_ready","is_inferred"],"fullname":"stripe._v1_services.V1Services.confirmation_tokens","name":"confirmation_tokens","setter_type":null,"type":{".class":"AnyType","missing_import_name":null,"source_any":null,"type_of_any":1}}},"country_specs":{".class":"SymbolTableNode","implicit":true,"kind":"Mdef","node":{".class":"Var","flags":["is_ready","is_inferred"],"fullname":"stripe._v1_services.V1Services.country_specs","name":"country_specs","setter_type":null,"type":{".class":"AnyType","missing_import_name":null,"source_any":null,"type_of_any":1}}},"coupons":{".class":"SymbolTableNode","implicit":true,"kind":"Mdef","node":{".class":"Var","flags":["is_ready","is_inferred"],"fullname":"stripe._v1_services.V1Services.coupons","name":"coupons","setter_type":null,"type":{".class":"AnyType","missing_import_name":null,"source_any":null,"type_of_any":1}}},"credit_notes":{".class":"SymbolTableNode","implicit":true,"kind":"Mdef","node":{".class":"Var","flags":["is_ready","is_inferred"],"fullname":"stripe._v1_services.V1Services.credit_notes","name":"credit_notes","setter_type":null,"type":{".class":"AnyType","missing_import_name":null,"source_any":null,"type_of_any":1}}},"customer_sessions":{".class":"SymbolTableNode","implicit":true,"kind":"Mdef","node":{".class":"Var","flags":["is_ready","is_inferred"],"fullname":"stripe._v1_services.V1Services.customer_sessions","name":"customer_sessions","setter_type":null,"type":{".class":"AnyType","missing_import_name":null,"source_any":null,"type_of_any":1}}},"customers":{".class":"SymbolTableNode","implicit":true,"kind":"Mdef","node":{".class":"Var","flags":["is_ready","is_inferred"],"fullname":"stripe._v1_services.V1Services.customers","name":"customers","setter_type":null,"type":{".class":"AnyType","missing_import_name":null,"source_any":null,"type_of_any":1}}},"disputes":{".class":"SymbolTableNode","implicit":true,"kind":"Mdef","node":{".class":"Var","flags":["is_ready","is_inferred"],"fullname":"stripe._v1_services.V1Services.disputes","name":"disputes","setter_type":null,"type":{".class":"AnyType","missing_import_name":null,"source_any":null,"type_of_any":1}}},"entitlements":{".class":"SymbolTableNode","implicit":true,"kind":"Mdef","node":{".class":"Var","flags":["is_ready","is_inferred"],"fullname":"stripe._v1_services.V1Services.entitlements","name":"entitlements","setter_type":null,"type":{".class":"AnyType","missing_import_name":null,"source_any":null,"type_of_any":1}}},"ephemeral_keys":{".class":"SymbolTableNode","implicit":true,"kind":"Mdef","node":{".class":"Var","flags":["is_ready","is_inferred"],"fullname":"stripe._v1_services.V1Services.ephemeral_keys","name":"ephemeral_keys","setter_type":null,"type":{".class":"AnyType","missing_import_name":null,"source_any":null,"type_of_any":1}}},"events":{".class":"SymbolTableNode","implicit":true,"kind":"Mdef","node":{".class":"Var","flags":["is_ready","is_inferred"],"fullname":"stripe._v1_services.V1Services.events","name":"events","setter_type":null,"type":{".class":"AnyType","missing_import_name":null,"source_any":null,"type_of_any":1}}},"exchange_rates":{".class":"SymbolTableNode","implicit":true,"kind":"Mdef","node":{".class":"Var","flags":["is_ready","is_inferred"],"fullname":"stripe._v1_services.V1Services.exchange_rates","name":"exchange_rates","setter_type":null,"type":{".class":"AnyType","missing_import_name":null,"source_any":null,"type_of_any":1}}},"file_links":{".class":"SymbolTableNode","implicit":true,"kind":"Mdef","node":{".class":"Var","flags":["is_ready","is_inferred"],"fullname":"stripe._v1_services.V1Services.file_links","name":"file_links","setter_type":null,"type":{".class":"AnyType","missing_import_name":null,"source_any":null,"type_of_any":1}}},"files":{".class":"SymbolTableNode","implicit":true,"kind":"Mdef","node":{".class":"Var","flags":["is_ready","is_inferred"],"fullname":"stripe._v1_services.V1Services.files","name":"files","setter_type":null,"type":{".class":"AnyType","missing_import_name":null,"source_any":null,"type_of_any":1}}},"financial_connections":{".class":"SymbolTableNode","implicit":true,"kind":"Mdef","node":{".class":"Var","flags":["is_ready","is_inferred"],"fullname":"stripe._v1_services.V1Services.financial_connections","name":"financial_connections","setter_type":null,"type":{".class":"AnyType","missing_import_name":null,"source_any":null,"type_of_any":1}}},"forwarding":{".class":"SymbolTableNode","implicit":true,"kind":"Mdef","node":{".class":"Var","flags":["is_ready","is_inferred"],"fullname":"stripe._v1_services.V1Services.forwarding","name":"forwarding","setter_type":null,"type":{".class":"AnyType","missing_import_name":null,"source_any":null,"type_of_any":1}}},"identity":{".class":"SymbolTableNode","implicit":true,"kind":"Mdef","node":{".class":"Var","flags":["is_ready","is_inferred"],"fullname":"stripe._v1_services.V1Services.identity","name":"identity","setter_type":null,"type":{".class":"AnyType","missing_import_name":null,"source_any":null,"type_of_any":1}}},"invoice_items":{".class":"SymbolTableNode","implicit":true,"kind":"Mdef","node":{".class":"Var","flags":["is_ready","is_inferred"],"fullname":"stripe._v1_services.V1Services.invoice_items","name":"invoice_items","setter_type":null,"type":{".class":"AnyType","missing_import_name":null,"source_any":null,"type_of_any":1}}},"invoice_payments":{".class":"SymbolTableNode","implicit":true,"kind":"Mdef","node":{".class":"Var","flags":["is_ready","is_inferred"],"fullname":"stripe._v1_services.V1Services.invoice_payments","name":"invoice_payments","setter_type":null,"type":{".class":"AnyType","missing_import_name":null,"source_any":null,"type_of_any":1}}},"invoice_rendering_templates":{".class":"SymbolTableNode","implicit":true,"kind":"Mdef","node":{".class":"Var","flags":["is_ready","is_inferred"],"fullname":"stripe._v1_services.V1Services.invoice_rendering_templates","name":"invoice_rendering_templates","setter_type":null,"type":{".class":"AnyType","missing_import_name":null,"source_any":null,"type_of_any":1}}},"invoices":{".class":"SymbolTableNode","implicit":true,"kind":"Mdef","node":{".class":"Var","flags":["is_ready","is_inferred"],"fullname":"stripe._v1_services.V1Services.invoices","name":"invoices","setter_type":null,"type":{".class":"AnyType","missing_import_name":null,"source_any":null,"type_of_any":1}}},"issuing":{".class":"SymbolTableNode","implicit":true,"kind":"Mdef","node":{".class":"Var","flags":["is_ready","is_inferred"],"fullname":"stripe._v1_services.V1Services.issuing","name":"issuing","setter_type":null,"type":{".class":"AnyType","missing_import_name":null,"source_any":null,"type_of_any":1}}},"mandates":{".class":"SymbolTableNode","implicit":true,"kind":"Mdef","node":{".class":"Var","flags":["is_ready","is_inferred"],"fullname":"stripe._v1_services.V1Services.mandates","name":"mandates","setter_type":null,"type":{".class":"AnyType","missing_import_name":null,"source_any":null,"type_of_any":1}}},"payment_intents":{".class":"SymbolTableNode","implicit":true,"kind":"Mdef","node":{".class":"Var","flags":["is_ready","is_inferred"],"fullname":"stripe._v1_services.V1Services.payment_intents","name":"payment_intents","setter_type":null,"type":{".class":"AnyType","missing_import_name":null,"source_any":null,"type_of_any":1}}},"payment_links":{".class":"SymbolTableNode","implicit":true,"kind":"Mdef","node":{".class":"Var","flags":["is_ready","is_inferred"],"fullname":"stripe._v1_services.V1Services.payment_links","name":"payment_links","setter_type":null,"type":{".class":"AnyType","missing_import_name":null,"source_any":null,"type_of_any":1}}},"payment_method_configurations":{".class":"SymbolTableNode","implicit":true,"kind":"Mdef","node":{".class":"Var","flags":["is_ready","is_inferred"],"fullname":"stripe._v1_services.V1Services.payment_method_configurations","name":"payment_method_configurations","setter_type":null,"type":{".class":"AnyType","missing_import_name":null,"source_any":null,"type_of_any":1}}},"payment_method_domains":{".class":"SymbolTableNode","implicit":true,"kind":"Mdef","node":{".class":"Var","flags":["is_ready","is_inferred"],"fullname":"stripe._v1_services.V1Services.payment_method_domains","name":"payment_method_domains","setter_type":null,"type":{".class":"AnyType","missing_import_name":null,"source_any":null,"type_of_any":1}}},"payment_methods":{".class":"SymbolTableNode","implicit":true,"kind":"Mdef","node":{".class":"Var","flags":["is_ready","is_inferred"],"fullname":"stripe._v1_services.V1Services.payment_methods","name":"payment_methods","setter_type":null,"type":{".class":"AnyType","missing_import_name":null,"source_any":null,"type_of_any":1}}},"payouts":{".class":"SymbolTableNode","implicit":true,"kind":"Mdef","node":{".class":"Var","flags":["is_ready","is_inferred"],"fullname":"stripe._v1_services.V1Services.payouts","name":"payouts","setter_type":null,"type":{".class":"AnyType","missing_import_name":null,"source_any":null,"type_of_any":1}}},"plans":{".class":"SymbolTableNode","implicit":true,"kind":"Mdef","node":{".class":"Var","flags":["is_ready","is_inferred"],"fullname":"stripe._v1_services.V1Services.plans","name":"plans","setter_type":null,"type":{".class":"AnyType","missing_import_name":null,"source_any":null,"type_of_any":1}}},"prices":{".class":"SymbolTableNode","implicit":true,"kind":"Mdef","node":{".class":"Var","flags":["is_ready","is_inferred"],"fullname":"stripe._v1_services.V1Services.prices","name":"prices","setter_type":null,"type":{".class":"AnyType","missing_import_name":null,"source_any":null,"type_of_any":1}}},"products":{".class":"SymbolTableNode","implicit":true,"kind":"Mdef","node":{".class":"Var","flags":["is_ready","is_inferred"],"fullname":"stripe._v1_services.V1Services.products","name":"products","setter_type":null,"type":{".class":"AnyType","missing_import_name":null,"source_any":null,"type_of_any":1}}},"promotion_codes":{".class":"SymbolTableNode","implicit":true,"kind":"Mdef","node":{".class":"Var","flags":["is_ready","is_inferred"],"fullname":"stripe._v1_services.V1Services.promotion_codes","name":"promotion_codes","setter_type":null,"type":{".class":"AnyType","missing_import_name":null,"source_any":null,"type_of_any":1}}},"quotes":{".class":"SymbolTableNode","implicit":true,"kind":"Mdef","node":{".class":"Var","flags":["is_ready","is_inferred"],"fullname":"stripe._v1_services.V1Services.quotes","name":"quotes","setter_type":null,"type":{".class":"AnyType","missing_import_name":null,"source_any":null,"type_of_any":1}}},"radar":{".class":"SymbolTableNode","implicit":true,"kind":"Mdef","node":{".class":"Var","flags":["is_ready","is_inferred"],"fullname":"stripe._v1_services.V1Services.radar","name":"radar","setter_type":null,"type":{".class":"AnyType","missing_import_name":null,"source_any":null,"type_of_any":1}}},"refunds":{".class":"SymbolTableNode","implicit":true,"kind":"Mdef","node":{".class":"Var","flags":["is_ready","is_inferred"],"fullname":"stripe._v1_services.V1Services.refunds","name":"refunds","setter_type":null,"type":{".class":"AnyType","missing_import_name":null,"source_any":null,"type_of_any":1}}},"reporting":{".class":"SymbolTableNode","implicit":true,"kind":"Mdef","node":{".class":"Var","flags":["is_ready","is_inferred"],"fullname":"stripe._v1_services.V1Services.reporting","name":"reporting","setter_type":null,"type":{".class":"AnyType","missing_import_name":null,"source_any":null,"type_of_any":1}}},"reviews":{".class":"SymbolTableNode","implicit":true,"kind":"Mdef","node":{".class":"Var","flags":["is_ready","is_inferred"],"fullname":"stripe._v1_services.V1Services.reviews","name":"reviews","setter_type":null,"type":{".class":"AnyType","missing_import_name":null,"source_any":null,"type_of_any":1}}},"setup_attempts":{".class":"SymbolTableNode","implicit":true,"kind":"Mdef","node":{".class":"Var","flags":["is_ready","is_inferred"],"fullname":"stripe._v1_services.V1Services.setup_attempts","name":"setup_attempts","setter_type":null,"type":{".class":"AnyType","missing_import_name":null,"source_any":null,"type_of_any":1}}},"setup_intents":{".class":"SymbolTableNode","implicit":true,"kind":"Mdef","node":{".class":"Var","flags":["is_ready","is_inferred"],"fullname":"stripe._v1_services.V1Services.setup_intents","name":"setup_intents","setter_type":null,"type":{".class":"AnyType","missing_import_name":null,"source_any":null,"type_of_any":1}}},"shipping_rates":{".class":"SymbolTableNode","implicit":true,"kind":"Mdef","node":{".class":"Var","flags":["is_ready","is_inferred"],"fullname":"stripe._v1_services.V1Services.shipping_rates","name":"shipping_rates","setter_type":null,"type":{".class":"AnyType","missing_import_name":null,"source_any":null,"type_of_any":1}}},"sigma":{".class":"SymbolTableNode","implicit":true,"kind":"Mdef","node":{".class":"Var","flags":["is_ready","is_inferred"],"fullname":"stripe._v1_services.V1Services.sigma","name":"sigma","setter_type":null,"type":{".class":"AnyType","missing_import_name":null,"source_any":null,"type_of_any":1}}},"sources":{".class":"SymbolTableNode","implicit":true,"kind":"Mdef","node":{".class":"Var","flags":["is_ready","is_inferred"],"fullname":"stripe._v1_services.V1Services.sources","name":"sources","setter_type":null,"type":{".class":"AnyType","missing_import_name":null,"source_any":null,"type_of_any":1}}},"subscription_items":{".class":"SymbolTableNode","implicit":true,"kind":"Mdef","node":{".class":"Var","flags":["is_ready","is_inferred"],"fullname":"stripe._v1_services.V1Services.subscription_items","name":"subscription_items","setter_type":null,"type":{".class":"AnyType","missing_import_name":null,"source_any":null,"type_of_any":1}}},"subscription_schedules":{".class":"SymbolTableNode","implicit":true,"kind":"Mdef","node":{".class":"Var","flags":["is_ready","is_inferred"],"fullname":"stripe._v1_services.V1Services.subscription_schedules","name":"subscription_schedules","setter_type":null,"type":{".class":"AnyType","missing_import_name":null,"source_any":null,"type_of_any":1}}},"subscriptions":{".class":"SymbolTableNode","implicit":true,"kind":"Mdef","node":{".class":"Var","flags":["is_ready","is_inferred"],"fullname":"stripe._v1_services.V1Services.subscriptions","name":"subscriptions","setter_type":null,"type":{".class":"AnyType","missing_import_name":null,"source_any":null,"type_of_any":1}}},"tax":{".class":"SymbolTableNode","implicit":true,"kind":"Mdef","node":{".class":"Var","flags":["is_ready","is_inferred"],"fullname":"stripe._v1_services.V1Services.tax","name":"tax","setter_type":null,"type":{".class":"AnyType","missing_import_name":null,"source_any":null,"type_of_any":1}}},"tax_codes":{".class":"SymbolTableNode","implicit":true,"kind":"Mdef","node":{".class":"Var","flags":["is_ready","is_inferred"],"fullname":"stripe._v1_services.V1Services.tax_codes","name":"tax_codes","setter_type":null,"type":{".class":"AnyType","missing_import_name":null,"source_any":null,"type_of_any":1}}},"tax_ids":{".class":"SymbolTableNode","implicit":true,"kind":"Mdef","node":{".class":"Var","flags":["is_ready","is_inferred"],"fullname":"stripe._v1_services.V1Services.tax_ids","name":"tax_ids","setter_type":null,"type":{".class":"AnyType","missing_import_name":null,"source_any":null,"type_of_any":1}}},"tax_rates":{".class":"SymbolTableNode","implicit":true,"kind":"Mdef","node":{".class":"Var","flags":["is_ready","is_inferred"],"fullname":"stripe._v1_services.V1Services.tax_rates","name":"tax_rates","setter_type":null,"type":{".class":"AnyType","missing_import_name":null,"source_any":null,"type_of_any":1}}},"terminal":{".class":"SymbolTableNode","implicit":true,"kind":"Mdef","node":{".class":"Var","flags":["is_ready","is_inferred"],"fullname":"stripe._v1_services.V1Services.terminal","name":"terminal","setter_type":null,"type":{".class":"AnyType","missing_import_name":null,"source_any":null,"type_of_any":1}}},"test_helpers":{".class":"SymbolTableNode","implicit":true,"kind":"Mdef","node":{".class":"Var","flags":["is_ready","is_inferred"],"fullname":"stripe._v1_services.V1Services.test_helpers","name":"test_helpers","setter_type":null,"type":{".class":"AnyType","missing_import_name":null,"source_any":null,"type_of_any":1}}},"tokens":{".class":"SymbolTableNode","implicit":true,"kind":"Mdef","node":{".class":"Var","flags":["is_ready","is_inferred"],"fullname":"stripe._v1_services.V1Services.tokens","name":"tokens","setter_type":null,"type":{".class":"AnyType","missing_import_name":null,"source_any":null,"type_of_any":1}}},"topups":{".class":"SymbolTableNode","implicit":true,"kind":"Mdef","node":{".class":"Var","flags":["is_ready","is_inferred"],"fullname":"stripe._v1_services.V1Services.topups","name":"topups","setter_type":null,"type":{".class":"AnyType","missing_import_name":null,"source_any":null,"type_of_any":1}}},"transfers":{".class":"SymbolTableNode","implicit":true,"kind":"Mdef","node":{".class":"Var","flags":["is_ready","is_inferred"],"fullname":"stripe._v1_services.V1Services.transfers","name":"transfers","setter_type":null,"type":{".class":"AnyType","missing_import_name":null,"source_any":null,"type_of_any":1}}},"treasury":{".class":"SymbolTableNode","implicit":true,"kind":"Mdef","node":{".class":"Var","flags":["is_ready","is_inferred"],"fullname":"stripe._v1_services.V1Services.treasury","name":"treasury","setter_type":null,"type":{".class":"AnyType","missing_import_name":null,"source_any":null,"type_of_any":1}}},"webhook_endpoints":{".class":"SymbolTableNode","implicit":true,"kind":"Mdef","node":{".class":"Var","flags":["is_ready","is_inferred"],"fullname":"stripe._v1_services.V1Services.webhook_endpoints","name":"webhook_endpoints","setter_type":null,"type":{".class":"AnyType","missing_import_name":null,"source_any":null,"type_of_any":1}}}},"self_type":{".class":"TypeVarType","default":{".class":"AnyType","missing_import_name":null,"source_any":null,"type_of_any":4},"fullname":"stripe._v1_services.V1Services.Self","id":0,"name":"Self","namespace":"","upper_bound":"stripe._v1_services.V1Services","values":[],"variance":0},"slots":null,"tuple_type":null,"type_vars":[],"typeddict_type":null}},"WebhookEndpointService":{".class":"SymbolTableNode","cross_ref":"stripe._webhook_endpoint_service.WebhookEndpointService","kind":"Gdef"},"__annotations__":{".class":"SymbolTableNode","kind":"Gdef","node":{".class":"Var","flags":["is_ready"],"fullname":"stripe._v1_services.__annotations__","name":"__annotations__","setter_type":null,"type":{".class":"Instance","args":["builtins.str",{".class":"AnyType","missing_import_name":null,"source_any":null,"type_of_any":6}],"extra_attrs":null,"type_ref":"builtins.dict"}}},"__doc__":{".class":"SymbolTableNode","kind":"Gdef","node":{".class":"Var","flags":["is_ready"],"fullname":"stripe._v1_services.__doc__","name":"__doc__","setter_type":null,"type":"builtins.str"}},"__file__":{".class":"SymbolTableNode","kind":"Gdef","node":{".class":"Var","flags":["is_ready"],"fullname":"stripe._v1_services.__file__","name":"__file__","setter_type":null,"type":"builtins.str"}},"__name__":{".class":"SymbolTableNode","kind":"Gdef","node":{".class":"Var","flags":["is_ready"],"fullname":"stripe._v1_services.__name__","name":"__name__","setter_type":null,"type":"builtins.str"}},"__package__":{".class":"SymbolTableNode","kind":"Gdef","node":{".class":"Var","flags":["is_ready"],"fullname":"stripe._v1_services.__package__","name":"__package__","setter_type":null,"type":"builtins.str"}},"__spec__":{".class":"SymbolTableNode","kind":"Gdef","node":{".class":"Var","flags":["is_ready"],"fullname":"stripe._v1_services.__spec__","name":"__spec__","setter_type":null,"type":"_frozen_importlib.ModuleSpec"}}},"path":"C:\\Users\\nirma\\AppData\\Local\\Programs\\Python\\Python313\\Lib\\site-packages\\stripe\\_v1_services.py"}