{".class":"MypyFile","_fullname":"app.shared.domain","future_import_flags":[],"is_partial_stub_package":false,"is_stub":false,"names":{".class":"SymbolTable","AggregateRoot":{".class":"SymbolTableNode","cross_ref":"app.shared.domain.base.AggregateRoot","kind":"Gdef"},"BaseEntity":{".class":"SymbolTableNode","cross_ref":"app.shared.domain.base.BaseEntity","kind":"Gdef"},"DomainEvent":{".class":"SymbolTableNode","cross_ref":"app.shared.domain.base.DomainEvent","kind":"Gdef"},"PostVisibility":{".class":"SymbolTableNode","cross_ref":"app.shared.domain.value_objects.PostVisibility","kind":"Gdef"},"UserRole":{".class":"SymbolTableNode","cross_ref":"app.shared.domain.value_objects.UserRole","kind":"Gdef"},"VideoStatus":{".class":"SymbolTableNode","cross_ref":"app.shared.domain.value_objects.VideoStatus","kind":"Gdef"},"VideoVisibility":{".class":"SymbolTableNode","cross_ref":"app.shared.domain.value_objects.VideoVisibility","kind":"Gdef"},"__all__":{".class":"SymbolTableNode","kind":"Gdef","module_public":false,"node":{".class":"Var","flags":["is_ready","is_inferred","has_explicit_value"],"fullname":"app.shared.domain.__all__","name":"__all__","setter_type":null,"type":{".class":"Instance","args":["builtins.str"],"extra_attrs":null,"type_ref":"builtins.list"}}},"__annotations__":{".class":"SymbolTableNode","kind":"Gdef","module_public":false,"node":{".class":"Var","flags":["is_ready"],"fullname":"app.shared.domain.__annotations__","name":"__annotations__","setter_type":null,"type":{".class":"Instance","args":["builtins.str",{".class":"AnyType","missing_import_name":null,"source_any":null,"type_of_any":6}],"extra_attrs":null,"type_ref":"builtins.dict"}}},"__doc__":{".class":"SymbolTableNode","kind":"Gdef","module_public":false,"node":{".class":"Var","flags":["is_ready"],"fullname":"app.shared.domain.__doc__","name":"__doc__","setter_type":null,"type":"builtins.str"}},"__file__":{".class":"SymbolTableNode","kind":"Gdef","module_public":false,"node":{".class":"Var","flags":["is_ready"],"fullname":"app.shared.domain.__file__","name":"__file__","setter_type":null,"type":"builtins.str"}},"__name__":{".class":"SymbolTableNode","kind":"Gdef","module_public":false,"node":{".class":"Var","flags":["is_ready"],"fullname":"app.shared.domain.__name__","name":"__name__","setter_type":null,"type":"builtins.str"}},"__package__":{".class":"SymbolTableNode","kind":"Gdef","module_public":false,"node":{".class":"Var","flags":["is_ready"],"fullname":"app.shared.domain.__package__","name":"__package__","setter_type":null,"type":"builtins.str"}},"__path__":{".class":"SymbolTableNode","kind":"Gdef","module_public":false,"node":{".class":"Var","flags":["is_ready"],"fullname":"app.shared.domain.__path__","name":"__path__","setter_type":null,"type":{".class":"Instance","args":["builtins.str"],"extra_attrs":null,"type_ref":"builtins.list"}}},"__spec__":{".class":"SymbolTableNode","kind":"Gdef","module_public":false,"node":{".class":"Var","flags":["is_ready"],"fullname":"app.shared.domain.__spec__","name":"__spec__","setter_type":null,"type":"_frozen_importlib.ModuleSpec"}}},"path":"app\\shared\\domain\\__init__.py"}